{
      "7c": {
            "1e-06": {
                  "train_accuracies": [
                        0.10450053215026855,
                        0.10487891733646393,
                        0.10507924109697342,
                        0.10541310906410217,
                        0.10583600401878357,
                        0.10610309988260269,
                        0.10645922273397446,
                        0.10701566934585571,
                        0.10703792423009872,
                        0.10734953731298447
                  ],
                  "val_accuracies": [
                        0.09880000352859497,
                        0.09860000014305115,
                        0.09880000352859497,
                        0.0989999994635582,
                        0.09939999878406525,
                        0.0997999981045723,
                        0.10019999742507935,
                        0.10019999742507935,
                        0.10119999945163727,
                        0.10180000215768814
                  ],
                  "test_accuracy": 0.10760000348091125,
                  "training_loss": [
                        2.3148124014210496,
                        2.3145731120367676,
                        2.3143067869365725,
                        2.3139697493311346,
                        2.3137947473770533,
                        2.3136059225794257,
                        2.313348905992644,
                        2.313082534023839,
                        2.3128892995013812,
                        2.3126223291087356
                  ],
                  "validation_loss": [
                        2.3146485447883607,
                        2.314412534236908,
                        2.314177167415619,
                        2.3139421463012697,
                        2.313707637786865,
                        2.3134737849235534,
                        2.313240295648575,
                        2.313007253408432,
                        2.3127747058868406,
                        2.3125427961349487
                  ]
            },
            "1e-05": {
                  "train_accuracies": [
                        0.10616987198591232,
                        0.10901887714862823,
                        0.11209045350551605,
                        0.1158965453505516,
                        0.11916844546794891,
                        0.12268518656492233,
                        0.12658031284809113,
                        0.13027510046958923,
                        0.13370281457901,
                        0.1373753547668457
                  ],
                  "val_accuracies": [
                        0.10180000215768814,
                        0.10440000146627426,
                        0.10719999670982361,
                        0.11020000278949738,
                        0.11559999734163284,
                        0.11959999799728394,
                        0.12559999525547028,
                        0.12960000336170197,
                        0.1348000019788742,
                        0.13680000603199005
                  ],
                  "test_accuracy": 0.1404999941587448,
                  "training_loss": [
                        2.313732388352397,
                        2.311344732925763,
                        2.308982972745542,
                        2.3065917254173516,
                        2.30440764549451,
                        2.3022653710128913,
                        2.3000885489319804,
                        2.297952687978065,
                        2.2959217882563925,
                        2.293879837052435
                  ],
                  "validation_loss": [
                        2.3125433743000032,
                        2.3102479219436645,
                        2.30800062417984,
                        2.3057977497577666,
                        2.3036392867565154,
                        2.3015259504318237,
                        2.2994550466537476,
                        2.2974275052547455,
                        2.2954411923885347,
                        2.293497198820114
                  ]
            },
            "0.0001": {
                  "train_accuracies": [
                        0.12119390815496445,
                        0.15411324799060822,
                        0.17603722214698792,
                        0.18870192766189575,
                        0.19742698967456818,
                        0.20274661481380463,
                        0.20695334672927856,
                        0.20935718715190887,
                        0.2122507095336914,
                        0.21425391733646393
                  ],
                  "val_accuracies": [
                        0.13660000264644623,
                        0.16200000047683716,
                        0.17820000648498535,
                        0.18860000371932983,
                        0.19499999284744263,
                        0.19760000705718994,
                        0.20160000026226044,
                        0.2046000063419342,
                        0.20679999887943268,
                        0.2093999981880188
                  ],
                  "test_accuracy": 0.210099995136261,
                  "training_loss": [
                        2.3036327511496695,
                        2.283685987831181,
                        2.267393349921941,
                        2.2536480223011766,
                        2.2419619913454407,
                        2.231703304497265,
                        2.2223863071865506,
                        2.213911048367492,
                        2.206055376264784,
                        2.198792801283703
                  ],
                  "validation_loss": [
                        2.2935104191303255,
                        2.2760744094848633,
                        2.261690783500671,
                        2.2494693219661714,
                        2.238809233903885,
                        2.22929961681366,
                        2.220689815282822,
                        2.2127831399440767,
                        2.205422592163086,
                        2.1985267817974092
                  ]
            },
            "0.001": {
                  "train_accuracies": [
                        0.18821224570274353,
                        0.2246260643005371,
                        0.24200943112373352,
                        0.2612402141094208,
                        0.27659812569618225,
                        0.29093214869499207,
                        0.30201655626296997,
                        0.3129896819591522,
                        0.32300570607185364,
                        0.3326655924320221
                  ],
                  "val_accuracies": [
                        0.20900000631809235,
                        0.23119999468326569,
                        0.2542000114917755,
                        0.2703999876976013,
                        0.2825999855995178,
                        0.29179999232292175,
                        0.303600013256073,
                        0.31220000982284546,
                        0.3222000002861023,
                        0.3325999975204468
                  ],
                  "test_accuracy": 0.33160001039505005,
                  "training_loss": [
                        2.242987030931348,
                        2.165935915759486,
                        2.1169041089522533,
                        2.0760640656506575,
                        2.040580376600608,
                        2.0090872545187968,
                        1.9808447235330218,
                        1.9553030532309812,
                        1.9321455208324638,
                        1.910876982572072
                  ],
                  "validation_loss": [
                        2.1989057302474975,
                        2.1435292303562163,
                        2.100739377737045,
                        2.0640741914510725,
                        2.0310671746730806,
                        2.001514133810997,
                        1.9752290457487107,
                        1.9509349763393402,
                        1.9289313495159148,
                        1.908618199825287
                  ]
            },
            "0.01": {
                  "train_accuracies": [
                        0.27029913663864136,
                        0.36168980598449707,
                        0.3897569477558136,
                        0.411925733089447,
                        0.42844104766845703,
                        0.4435763955116272,
                        0.4531472623348236,
                        0.46692484617233276,
                        0.4746705889701843,
                        0.48145923018455505
                  ],
                  "val_accuracies": [
                        0.3303999900817871,
                        0.3707999885082245,
                        0.39500001072883606,
                        0.4113999903202057,
                        0.42500001192092896,
                        0.428600013256073,
                        0.44600000977516174,
                        0.45080000162124634,
                        0.4564000070095062,
                        0.46059998869895935
                  ],
                  "test_accuracy": 0.46939998865127563,
                  "training_loss": [
                        2.048141410887411,
                        1.8336069740121521,
                        1.7407041570739528,
                        1.6797899303273258,
                        1.631108377054546,
                        1.5919456434385728,
                        1.5596924123601017,
                        1.529679737539373,
                        1.502201428780189,
                        1.4758300268412317
                  ],
                  "validation_loss": [
                        1.912202149629593,
                        1.782677134871483,
                        1.71285979449749,
                        1.6753191739320754,
                        1.6283067256212234,
                        1.6085267573595048,
                        1.5775995314121247,
                        1.5536484211683272,
                        1.5376972943544387,
                        1.5205093234777451
                  ]
            },
            "0.1": {
                  "train_accuracies": [
                        0.3703926205635071,
                        0.4400818943977356,
                        0.4704638421535492,
                        0.49403488636016846,
                        0.511729896068573,
                        0.5258635878562927,
                        0.5346999764442444,
                        0.5504807829856873,
                        0.5550658702850342,
                        0.5642583966255188
                  ],
                  "val_accuracies": [
                        0.42480000853538513,
                        0.4413999915122986,
                        0.47679999470710754,
                        0.47699999809265137,
                        0.4713999927043915,
                        0.48899999260902405,
                        0.48660001158714294,
                        0.46540001034736633,
                        0.501800000667572,
                        0.4984000027179718
                  ],
                  "test_accuracy": 0.5047000050544739,
                  "training_loss": [
                        1.7683215789985114,
                        1.571534727034066,
                        1.487980070277157,
                        1.42677599921865,
                        1.3801352627936252,
                        1.3384191151018496,
                        1.3119146380669031,
                        1.276429435806057,
                        1.2471479269174428,
                        1.224602112233469
                  ],
                  "validation_loss": [
                        1.625355961918831,
                        1.5553707659244538,
                        1.4984925091266632,
                        1.468865630030632,
                        1.473834639787674,
                        1.4455781280994415,
                        1.4491852581501008,
                        1.5424714058637619,
                        1.428039026260376,
                        1.4467662066221236
                  ]
            },
            "1.0": {
                  "train_accuracies": [
                        0.10191862285137177,
                        0.09733351320028305,
                        0.09889155626296997,
                        0.10096153616905212,
                        0.09944800287485123,
                        0.10327634960412979,
                        0.09826833754777908,
                        0.09671029448509216,
                        0.10118411481380463,
                        0.09991542249917984
                  ],
                  "val_accuracies": [
                        0.10080000013113022,
                        0.10019999742507935,
                        0.10639999806880951,
                        0.10279999673366547,
                        0.094200000166893,
                        0.10279999673366547,
                        0.094200000166893,
                        0.10080000013113022,
                        0.094200000166893,
                        0.10019999742507935
                  ],
                  "test_accuracy": 0.10000000149011612,
                  "training_loss": [
                        40.864082263066216,
                        2.3489815346535794,
                        2.350045665376886,
                        2.3467248973683414,
                        2.3496603483488077,
                        2.3439772156229046,
                        2.3465162688850336,
                        2.3481363964895916,
                        2.346750715858916,
                        2.3455525592521385
                  ],
                  "validation_loss": [
                        2.3987795650959014,
                        2.399203300476074,
                        2.341994673013687,
                        2.358077746629715,
                        2.3391825199127196,
                        2.3485165417194365,
                        2.353615128993988,
                        2.3356249213218687,
                        2.3608956336975098,
                        2.397716593742371
                  ]
            },
            "10.0": {
                  "train_accuracies": [
                        0.09984865039587021,
                        0.09989316016435623,
                        0.09987090528011322,
                        0.09991542249917984,
                        0.09987090528011322,
                        0.09989316016435623,
                        0.09978187084197998,
                        0.09989316016435623,
                        0.09984865039587021,
                        0.09975961595773697
                  ],
                  "val_accuracies": [
                        0.10140000283718109,
                        0.10140000283718109,
                        0.10140000283718109,
                        0.10140000283718109,
                        0.10140000283718109,
                        0.10140000283718109,
                        0.10140000283718109,
                        0.10140000283718109,
                        0.10140000283718109,
                        0.10140000283718109
                  ],
                  "test_accuracy": 0.10000000149011612,
                  "training_loss": [
                        1599240189341680.2,
                        656583793037650.4,
                        656588694470235.9,
                        656545155539387.5,
                        656597694514552.4,
                        656562278241761.4,
                        656659503881423.1,
                        656575687969380.6,
                        656610202765551.2,
                        656663949126688.1
                  ],
                  "validation_loss": [
                        655626195697664.0,
                        655626195697664.0,
                        655626195697664.0,
                        655626195697664.0,
                        655626195697664.0,
                        655626195697664.0,
                        655626195697664.0,
                        655626195697664.0,
                        655626195697664.0,
                        655626195697664.0
                  ]
            },
            "100.0": {
                  "train_accuracies": [
                        0.10031606256961823,
                        0.10033831745386124,
                        0.1002492904663086,
                        0.10013800114393234,
                        0.1002492904663086,
                        0.1002492904663086,
                        0.10033831745386124,
                        0.10029380023479462,
                        0.1002715453505516,
                        0.10022702813148499
                  ],
                  "val_accuracies": [
                        0.09759999811649323,
                        0.09759999811649323,
                        0.09759999811649323,
                        0.09759999811649323,
                        0.09759999811649323,
                        0.09759999811649323,
                        0.09759999811649323,
                        0.09759999811649323,
                        0.09759999811649323,
                        0.09759999811649323
                  ],
                  "test_accuracy": 0.10000000149011612,
                  "training_loss": [
                        NaN,
                        NaN,
                        NaN,
                        NaN,
                        NaN,
                        NaN,
                        NaN,
                        NaN,
                        NaN,
                        NaN
                  ],
                  "validation_loss": [
                        NaN,
                        NaN,
                        NaN,
                        NaN,
                        NaN,
                        NaN,
                        NaN,
                        NaN,
                        NaN,
                        NaN
                  ]
            }
      },
      "8f": {
            "[128]": {
                  "train_accuracies": [
                        0.3703926205635071,
                        0.4400818943977356,
                        0.4704638421535492,
                        0.49403488636016846,
                        0.511729896068573,
                        0.5258635878562927,
                        0.5346999764442444,
                        0.5504807829856873,
                        0.5550658702850342,
                        0.5642583966255188,
                        0.5703347325325012,
                        0.5813746452331543,
                        0.5867610573768616,
                        0.5924590229988098,
                        0.6045227646827698,
                        0.6113336682319641,
                        0.6161859035491943,
                        0.6236200332641602,
                        0.6302973628044128,
                        0.6347267031669617
                  ],
                  "val_accuracies": [
                        0.42480000853538513,
                        0.4413999915122986,
                        0.47679999470710754,
                        0.47699999809265137,
                        0.4713999927043915,
                        0.48899999260902405,
                        0.48660001158714294,
                        0.46540001034736633,
                        0.501800000667572,
                        0.4984000027179718,
                        0.4959999918937683,
                        0.49779999256134033,
                        0.503600001335144,
                        0.4875999987125397,
                        0.5109999775886536,
                        0.5058000087738037,
                        0.4896000027656555,
                        0.5063999891281128,
                        0.5145999789237976,
                        0.5091999769210815
                  ],
                  "test_accuracy": 0.5166000127792358,
                  "training_loss": [
                        1.7683215789985114,
                        1.571534727034066,
                        1.487980070277157,
                        1.42677599921865,
                        1.3801352627936252,
                        1.3384191151018496,
                        1.3119146380669031,
                        1.276429435806057,
                        1.2471479269174428,
                        1.224602112233469,
                        1.1984502088989628,
                        1.1780221345078232,
                        1.1620463627016442,
                        1.1408610350725659,
                        1.1168526321055203,
                        1.0981356372520794,
                        1.0795182492318656,
                        1.0639043331485867,
                        1.0464100781668964,
                        1.0324408418772228
                  ],
                  "validation_loss": [
                        1.625355961918831,
                        1.5553707659244538,
                        1.4984925091266632,
                        1.468865630030632,
                        1.473834639787674,
                        1.4455781280994415,
                        1.4491852581501008,
                        1.5424714058637619,
                        1.428039026260376,
                        1.4467662066221236,
                        1.45881427526474,
                        1.4620134770870208,
                        1.436459121108055,
                        1.4447048231959343,
                        1.4389467597007752,
                        1.4742325067520141,
                        1.5021179884672164,
                        1.449843516945839,
                        1.4724864810705185,
                        1.5060088872909545
                  ]
            },
            "[256, 128]": {
                  "train_accuracies": [
                        0.36551815271377563,
                        0.44911858439445496,
                        0.4880920648574829,
                        0.5127982497215271,
                        0.5359464287757874,
                        0.5552884340286255,
                        0.5703792572021484,
                        0.5912793874740601,
                        0.6081953644752502,
                        0.6239093542098999,
                        0.6379762887954712,
                        0.6512642502784729,
                        0.6659544110298157,
                        0.6797320246696472,
                        0.6928864121437073,
                        0.7072649598121643,
                        0.7198406457901001,
                        0.7331730723381042,
                        0.739160418510437,
                        0.7560541033744812
                  ],
                  "val_accuracies": [
                        0.4092000126838684,
                        0.44359999895095825,
                        0.487199991941452,
                        0.4880000054836273,
                        0.5162000060081482,
                        0.5246000289916992,
                        0.5224000215530396,
                        0.521399974822998,
                        0.534600019454956,
                        0.532800018787384,
                        0.5163999795913696,
                        0.5406000018119812,
                        0.5307999849319458,
                        0.526199996471405,
                        0.5049999952316284,
                        0.5321999788284302,
                        0.5257999897003174,
                        0.5123999714851379,
                        0.522599995136261,
                        0.5185999870300293
                  ],
                  "test_accuracy": 0.542900025844574,
                  "training_loss": [
                        1.7792951462954878,
                        1.5629722963371169,
                        1.4515611221987297,
                        1.3696312452653194,
                        1.3069235561919688,
                        1.2478501397659976,
                        1.1975553636876946,
                        1.1476809375646106,
                        1.1003790866275798,
                        1.055774882648066,
                        1.0166981709309113,
                        0.976328037403248,
                        0.9367213765440503,
                        0.8963041799700159,
                        0.8622264403563279,
                        0.8241247059273245,
                        0.7871400240140084,
                        0.7524506556682098,
                        0.7328299993803019,
                        0.6874709791607327
                  ],
                  "validation_loss": [
                        1.66484677195549,
                        1.554438865184784,
                        1.4402849167585372,
                        1.4557080805301665,
                        1.3744716078042984,
                        1.3367047280073165,
                        1.3631117582321166,
                        1.3614112198352815,
                        1.3448156863451004,
                        1.3754813939332962,
                        1.4561610281467439,
                        1.3948188722133636,
                        1.4388932973146438,
                        1.457037737965584,
                        1.5699836641550065,
                        1.4849612027406693,
                        1.5489527821540832,
                        1.6387907147407532,
                        1.6389138877391816,
                        1.6671926438808442
                  ]
            },
            "[512, 256, 128]": {
                  "train_accuracies": [
                        0.3434829115867615,
                        0.4357416331768036,
                        0.47598379850387573,
                        0.5061209201812744,
                        0.5286012887954712,
                        0.5519720315933228,
                        0.5681535005569458,
                        0.5880074501037598,
                        0.6060808300971985,
                        0.6217725872993469,
                        0.6386440396308899,
                        0.6561832427978516,
                        0.6728765964508057,
                        0.6889244914054871,
                        0.7055956125259399,
                        0.7217102646827698,
                        0.7416755557060242,
                        0.7525373697280884,
                        0.770432710647583,
                        0.7840989828109741
                  ],
                  "val_accuracies": [
                        0.4099999964237213,
                        0.45080000162124634,
                        0.48500001430511475,
                        0.4909999966621399,
                        0.522599995136261,
                        0.5058000087738037,
                        0.5185999870300293,
                        0.5350000262260437,
                        0.5379999876022339,
                        0.534600019454956,
                        0.5371999740600586,
                        0.5378000140190125,
                        0.5486000180244446,
                        0.545799970626831,
                        0.5320000052452087,
                        0.5483999848365784,
                        0.5311999917030334,
                        0.5289999842643738,
                        0.5429999828338623,
                        0.5293999910354614
                  ],
                  "test_accuracy": 0.536899983882904,
                  "training_loss": [
                        1.8310714929531782,
                        1.5824522421910212,
                        1.4712829087194894,
                        1.3887491674504728,
                        1.31890372842805,
                        1.2563742990167732,
                        1.2066185926100468,
                        1.1551386508506927,
                        1.103177986593328,
                        1.0583280606826826,
                        1.0104134765445676,
                        0.9615469975688858,
                        0.9170226108314644,
                        0.874758600849032,
                        0.8269314337999393,
                        0.7811067425287687,
                        0.7265068503186913,
                        0.6921705987378742,
                        0.6462584163388635,
                        0.607821785911196
                  ],
                  "validation_loss": [
                        1.664200910925865,
                        1.5500097423791885,
                        1.4561496645212173,
                        1.4373563945293426,
                        1.3565673500299453,
                        1.4077241003513337,
                        1.3665552884340286,
                        1.324928417801857,
                        1.3180407524108886,
                        1.336789646744728,
                        1.3613951325416564,
                        1.3764221578836442,
                        1.3900077760219574,
                        1.4087837100028993,
                        1.4878281205892563,
                        1.4838317543268205,
                        1.583803591132164,
                        1.6128404825925826,
                        1.6341094970703125,
                        1.7716867208480835
                  ]
            }
      }
}